teleddns/__init__.py
teleddns-0.1.5.dist-info/LICENSE
teleddns-0.1.5.dist-info/METADATA
teleddns-0.1.5.dist-info/WHEEL
teleddns-0.1.5.dist-info/entry_points.txt
teleddns-0.1.5.dist-info/RECORD
