Metadata-Version: 2.1
Name: teleddns
Version: 0.1.5
Summary: Telephant Linux DDNS client
Home-page: https://www.telephant.eu/
License: GPL-3.0-or-later
Author: Tomas Hlavacek
Author-email: tmshlvck@gmail.com
Requires-Python: >=3.8,<4.0
Classifier: License :: OSI Approved :: GNU General Public License v3 or later (GPLv3+)
Classifier: Programming Language :: Python :: 3
Classifier: Programming Language :: Python :: 3.8
Classifier: Programming Language :: Python :: 3.9
Classifier: Programming Language :: Python :: 3.10
Classifier: Programming Language :: Python :: 3.11
Classifier: Programming Language :: Python :: 3.12
Requires-Dist: click
Requires-Dist: passlib (>=1.7.4,<2.0.0)
Requires-Dist: pyroute2 (>=0.7.12,<0.8.0)
Requires-Dist: pyyaml
Requires-Dist: requests (>=2.27,<3.0)
Project-URL: Repository, https://github.com/tmshlvck/teleddns
